{
  "20231201": {
    "url": "https://www.bing.com/th?id=OHR.TrotternishStorr_EN-CA5599802740_1920x1080.jpg",
    "date": "2023-12-01",
    "title": "The Old Man on his watch",
    "copyright": "The Storr, a rock outcrop on the Isle of Skye, Scotland (© Juan Maria Coy Vergara/Getty Images)",
    "copyrightlink": "https://www.bing.com/search?q=Saint+Andrew%27s+Day+Scotland&form=hpcapt&filters=HpDate%3a%2220231130_0500%22"
  },
  "20231202": {
    "url": "https://www.bing.com/th?id=OHR.MinnewankaLake_EN-CA2495233289_1920x1080.jpg",
    "date": "2023-12-02",
    "title": "Starlight, shining bright",
    "copyright": "Lake Minnewanka, Alberta, Canada (© Ken Phung/500px/Getty Images)",
    "copyrightlink": "https://www.bing.com/search?q=Lake+Minnewanka+Alberta&form=hpcapt&filters=HpDate%3a%2220231201_0500%22"
  },
  "20231203": {
    "url": "https://www.bing.com/th?id=OHR.AngkorPark_EN-CA3208481689_1920x1080.jpg",
    "date": "2023-12-03",
    "title": "A city within a city",
    "copyright": "North Gate of Angkor Thom, Angkor Archaeological Park, Cambodia (© Amazing Travel Lifestyle/Shutterstock)",
    "copyrightlink": "https://www.bing.com/search?q=Angkor+Cambodia&form=hpcapt&filters=HpDate%3a%2220231202_0500%22"
  },
  "20231204": {
    "url": "https://www.bing.com/th?id=OHR.VermilionCliffs_EN-CA1719361824_1920x1080.jpg",
    "date": "2023-12-04",
    "title": "Sculpted by time",
    "copyright": "Sandstone rock formations, Vermilion Cliffs National Monument, Arizona (© Yva Momatiuk and John Eastcott/Minden Pictures)",
    "copyrightlink": "https://www.bing.com/search?q=Vermilion+Cliffs+National+Monument&form=hpcapt&filters=HpDate%3a%2220231203_0500%22"
  },
  "20231205": {
    "url": "https://www.bing.com/th?id=OHR.CheetahDay_EN-CA9596172993_1920x1080.jpg",
    "date": "2023-12-05",
    "title": "Masters of agility and cuteness",
    "copyright": "A mother cheetah and her cubs in the Masai Mara National Reserve, Kenya (© Scott Davis/Tandem Stills + Motion)",
    "copyrightlink": "https://www.bing.com/search?q=Cheetah+animal&form=hpcapt&filters=HpDate%3a%2220231204_0500%22"
  },
  "20231206": {
    "url": "https://www.bing.com/th?id=OHR.AlpsCastles_EN-CA3984381282_1920x1080.jpg",
    "date": "2023-12-06",
    "title": "Straight out of a fairytale",
    "copyright": "Neuschwanstein and Hohenschwangau Castles, Bavarian Alps, Germany (© Harald Nachtmann/Getty Images)",
    "copyrightlink": "https://www.bing.com/search?q=Neuschwanstein+and+Hohenschwangau+Castles&form=hpcapt&filters=HpDate%3a%2220231205_0500%22"
  },
  "20231207": {
    "url": "https://www.bing.com/th?id=OHR.CERNCenter_EN-CA4364715980_1920x1080.jpg",
    "date": "2023-12-07",
    "title": "A global code for the future",
    "copyright": "The Globe of Science and Innovation building, Meyrin, Switzerland (© Deyan Baric/Alamy)",
    "copyrightlink": "https://www.bing.com/search?q=Computer+Science+Week&form=hpcapt&filters=HpDate%3a%2220231206_0500%22"
  },
  "20231208": {
    "url": "https://www.bing.com/th?id=OHR.GrandCanyonVerdon_EN-CA6319133080_1920x1080.jpg",
    "date": "2023-12-08",
    "title": "Don't let the clouds fool you!",
    "copyright": "A foggy morning at Verdon Gorge in the Alpes-de-Haute-Provence of France (© Hemis/Alamy)",
    "copyrightlink": "https://www.bing.com/search?q=Verdon+Gorge&form=hpcapt&filters=HpDate%3a%2220231207_0500%22"
  },
  "20231209": {
    "url": "https://www.bing.com/th?id=OHR.JerseyIsland_EN-CA2533906685_1920x1080.jpg",
    "date": "2023-12-09",
    "title": "Not that Jersey Shore Not that Jersey Shore",
    "copyright": "La Rocque Harbour, St. Clement, Island of Jersey (© Reinhard Schmid/Huber/eStock Photo)",
    "copyrightlink": "https://www.bing.com/search?q=Jersey+Island&form=hpcapt&filters=HpDate%3a%2220231208_0500%22"
  },
  "20231210": {
    "url": "https://www.bing.com/th?id=OHR.PatagoniaGuanaco_EN-CA9262708523_1920x1080.jpg",
    "date": "2023-12-10",
    "title": "Llamas on the loose",
    "copyright": "Guanacos in Los Glaciares National Park, Patagonia, Argentina (© Yva Momatiuk and John Eastcott/Minden Pictures)",
    "copyrightlink": "https://www.bing.com/search?q=llama+animal&form=hpcapt&filters=HpDate%3a%2220231209_0500%22"
  },
  "20231211": {
    "url": "https://www.bing.com/th?id=OHR.SaharaDunes_EN-CA5200526907_1920x1080.jpg",
    "date": "2023-12-11",
    "title": "Each day a different dune",
    "copyright": "Last rays of sun on a group of dunes, Sahara, Algeria (© AWL Images/DanitaDelimont.com)",
    "copyrightlink": "https://www.bing.com/search?q=Sahara+desert&form=hpcapt&filters=HpDate%3a%2220231210_0500%22"
  },
  "20231212": {
    "url": "https://www.bing.com/th?id=OHR.MountainDayChina_EN-CA0225759404_1920x1080.jpg",
    "date": "2023-12-12",
    "title": "Care for a peak?",
    "copyright": "Winter in Huangshan Mountains, China (© Hung Chung Chih/Shutterstock)",
    "copyrightlink": "https://www.bing.com/search?q=Huangshan+Mountains+China&form=hpcapt&filters=HpDate%3a%2220231211_0500%22"
  },
  "20231213": {
    "url": "https://www.bing.com/th?id=OHR.Poinsettia_EN-CA0341859998_1920x1080.jpg",
    "date": "2023-12-13",
    "title": "Paint your world red",
    "copyright": "Red poinsettias (© Yarygin/Getty Images)",
    "copyrightlink": "https://www.bing.com/search?q=Poinsettia&form=hpcapt&filters=HpDate%3a%2220231212_0500%22"
  },
  "20231214": {
    "url": "https://www.bing.com/th?id=OHR.LofotenRorbu_EN-CA0505973846_1920x1080.jpg",
    "date": "2023-12-14",
    "title": "Life in a hut-shell",
    "copyright": "Traditional fishing cabins, Svolvaer, Lofoten Islands, Norway (© Roberto Moiola/Sysaworld/Getty Images)",
    "copyrightlink": "https://www.bing.com/search?q=Svolvaer&form=hpcapt&filters=HpDate%3a%2220231213_0500%22"
  },
  "20231215": {
    "url": "https://www.bing.com/th?id=OHR.BorealOwl_EN-CA5986329708_1920x1080.jpg",
    "date": "2023-12-15",
    "title": "Owl in one",
    "copyright": "Boreal owl, Saskatchewan, Canada (© Nick Saunders/Minden Pictures)",
    "copyrightlink": "https://www.bing.com/search?q=Boreal+owl&form=hpcapt&filters=HpDate%3a%2220231214_0500%22"
  },
  "20231216": {
    "url": "https://www.bing.com/th?id=OHR.SantaPark_EN-CA4150572624_1920x1080.jpg",
    "date": "2023-12-16",
    "title": "Santa's playground",
    "copyright": "SantaPark in Rovaniemi, Lapland, Finland (© lukutin77/Getty Images)",
    "copyrightlink": "https://www.bing.com/search?q=SantaPark+Finland&form=hpcapt&filters=HpDate%3a%2220231215_0500%22"
  },
  "20231217": {
    "url": "https://www.bing.com/th?id=OHR.GrandPlaceXmas_EN-CA4794374028_1920x1080.jpg",
    "date": "2023-12-17",
    "title": "A cheerful case of the blues",
    "copyright": "Guild houses of Grand-Place, Brussels, Belgium (© Richard Taylor/Sime/eStock Photo)",
    "copyrightlink": "https://www.bing.com/search?q=Grand+Place+Belgium&form=hpcapt&filters=HpDate%3a%2220231216_0500%22"
  },
  "20231218": {
    "url": "https://www.bing.com/th?id=OHR.WinterWaxwings_EN-CA5729740430_1920x1080.jpg",
    "date": "2023-12-18",
    "title": "Feathered fashionistas",
    "copyright": "Bohemian waxwings perched on a branch, Canada (© Jim Cumming/Shutterstock)",
    "copyrightlink": "https://www.bing.com/search?q=Bohemian+waxwings&form=hpcapt&filters=HpDate%3a%2220231217_0500%22"
  },
  "20231219": {
    "url": "https://www.bing.com/th?id=OHR.CapitolReefSnow_EN-CA8234671064_1920x1080.jpg",
    "date": "2023-12-19",
    "title": "Snow, snow on the range",
    "copyright": "Capitol Reef National Park, Utah (© Jeff Clay/Tandem Stills + Motion)",
    "copyrightlink": "https://www.bing.com/search?q=Capitol+Reef+National+Park&form=hpcapt&filters=HpDate%3a%2220231218_0500%22"
  },
  "20231220": {
    "url": "https://www.bing.com/th?id=OHR.WarsawChristmas_EN-CA8636776898_1920x1080.jpg",
    "date": "2023-12-20",
    "title": "Santa's Polish rest stop",
    "copyright": "Christmas tree in Castle Square, Old Town, Warsaw, Poland (© Panther Media GmbH/Alamy)",
    "copyrightlink": "https://www.bing.com/search?q=Castle+Square+Old+Town+Warsaw&form=hpcapt&filters=HpDate%3a%2220231219_0500%22"
  },
  "20231221": {
    "url": "https://www.bing.com/th?id=OHR.ValGardenaItaly_EN-CA9038547102_1920x1080.jpg",
    "date": "2023-12-21",
    "title": "Lights of the Dolomites",
    "copyright": "Village in Val Gardena at Christmas, Dolomites, Italy (© Ingus Kruklitis/Getty Images)",
    "copyrightlink": "https://www.bing.com/search?q=Val+Gardena+South+Tyrol&form=hpcapt&filters=HpDate%3a%2220231220_0500%22"
  },
  "20231222": {
    "url": "https://www.bing.com/th?id=OHR.CastleriggStoneCircleUK_EN-CA9940011631_1920x1080.jpg",
    "date": "2023-12-22",
    "title": "Bring on the light",
    "copyright": "Castlerigg Stone Circle near Keswick, Lake District National Park, Cumbria, United Kingdom (© John Finney Photography/Getty Images)",
    "copyrightlink": "https://www.bing.com/search?q=December+solstice&form=hpcapt&filters=HpDate%3a%2220231221_0500%22"
  },
  "20231223": {
    "url": "https://www.bing.com/th?id=OHR.LjubljanaLights_EN-CA1534198321_1920x1080.jpg",
    "date": "2023-12-23",
    "title": "Holiday cheer, Slovenian style",
    "copyright": "Ljubljana, Slovenia (© kasto80/Getty images)",
    "copyrightlink": "https://www.bing.com/search?q=Ljubljana&form=hpcapt&filters=HpDate%3a%2220231222_0500%22"
  },
  "20231224": {
    "url": "https://www.bing.com/th?id=OHR.FestivusPenguins_EN-CA2075026889_1920x1080.jpg",
    "date": "2023-12-24",
    "title": "They've got some things to say",
    "copyright": "Chinstrap penguins, South Sandwich Islands, South Atlantic Ocean (© Jan Vermeer/Minden Pictures)",
    "copyrightlink": "https://www.bing.com/search?q=Festivus&form=hpcapt&filters=HpDate%3a%2220231223_0500%22"
  },
  "20231225": {
    "url": "https://www.bing.com/th?id=OHR.EstoniaXmasEve_EN-CA2639551026_1920x1080.jpg",
    "date": "2023-12-25",
    "title": "How lovely are your branches",
    "copyright": "Town Hall Square, Tartu, Estonia (© Westend61/Getty Images)",
    "copyrightlink": "https://www.bing.com/search?q=Tartu+Estonia&form=hpcapt&filters=HpDate%3a%2220231224_0500%22"
  },
  "20231226": {
    "url": "https://www.bing.com/th?id=OHR.ChristmasCA_EN-CA0839691287_1920x1080.jpg",
    "date": "2023-12-26",
    "title": "Merry Christmas!",
    "copyright": "Toronto Christmas market at the Distillery District (© Praveen P.N/Moment/Getty Images)",
    "copyrightlink": "https://www.bing.com/search?q=The+Distillery+District+Toronto&form=hpcapt&filters=HpDate%3a%2220231225_0500%22"
  },
  "20231227": {
    "url": "https://www.bing.com/th?id=OHR.BoxingDayCA_EN-CA7491018775_1920x1080.jpg",
    "date": "2023-12-27",
    "title": "Happy Boxing Day!",
    "copyright": "Christmas lights on trees at dusk, Vancouver, Canada (© Stuart Dee/Getty Images)",
    "copyrightlink": "https://www.bing.com/search?q=Boxing+day&form=hpcapt&filters=HpDate%3a%2220231226_0500%22"
  },
  "20231228": {
    "url": "https://www.bing.com/th?id=OHR.KirkjufellAurora_EN-CA8070468139_1920x1080.jpg",
    "date": "2023-12-28",
    "title": "The land of ice and fire",
    "copyright": "Kirkjufell, Snæfellsnes peninsula, Iceland (© Ratnakorn Piyasirisorost/Getty Images)",
    "copyrightlink": "https://www.bing.com/search?q=Kirkjufell+Iceland&form=hpcapt&filters=HpDate%3a%2220231227_0500%22"
  },
  "20231229": {
    "url": "https://www.bing.com/th?id=OHR.GreenlandHumpback_EN-CA8706019079_1920x1080.jpg",
    "date": "2023-12-29",
    "title": "Whale hello there",
    "copyright": "Humpback whale, Disko Bay, Greenland (© Paul Souders/DanitaDelimont.com)",
    "copyrightlink": "https://www.bing.com/search?q=Humpback+whale&form=hpcapt&filters=HpDate%3a%2220231228_0500%22"
  },
  "20231230": {
    "url": "https://www.bing.com/th?id=OHR.BlueAmsterdam_EN-CA0805614329_1920x1080.jpg",
    "date": "2023-12-30",
    "title": "Oud-West side story",
    "copyright": "Oud-West neighborhood, Amsterdam, Netherlands (© George Pachantouris/Getty Images)",
    "copyrightlink": "https://www.bing.com/search?q=Amsterdam+Netherlands&form=hpcapt&filters=HpDate%3a%2220231229_0500%22"
  },
  "20231231": {
    "url": "https://www.bing.com/th?id=OHR.TadamiWinter_EN-CA2053501506_1920x1080.jpg",
    "date": "2023-12-31",
    "title": "A journey over the bold blue",
    "copyright": "Daiichi Tadami River Bridge, Fukushima prefecture, Japan (© DoctorEgg/Getty Images)",
    "copyrightlink": "https://www.bing.com/search?q=Tadami+River&form=hpcapt&filters=HpDate%3a%2220231230_0500%22"
  }
}