{
  "20220701": {
    "url": "https://www.bing.com/th?id=OHR.WeatherGirls_FR-FR3672739777_1920x1080.jpg",
    "date": "2022-07-01",
    "title": "Les filles météo",
    "copyright": "La sculpture ‘Vejrpigerne’ (“Les filles météo”) dominant la place de la mairie à Copenhague, Danemark (© Stig Alenas/Shutterstock)",
    "copyrightlink": "https://www.bing.com/search?q=tour+de+france&form=hpcapt&filters=HpDate%3a%2220220630_2200%22"
  },
  "20220702": {
    "url": "https://www.bing.com/th?id=OHR.HalfwayDay_FR-FR4077214766_1920x1080.jpg",
    "date": "2022-07-02",
    "title": "À mi-chemin",
    "copyright": "Vue aérienne d’une route séparant deux lacs dans les Highlands d'Écosse (© Abstract Aerial Art/Getty Images)",
    "copyrightlink": "https://www.bing.com/search?q=highlands+%C3%A9cosse&form=hpcapt&filters=HpDate%3a%2220220701_2200%22"
  },
  "20220703": {
    "url": "https://www.bing.com/th?id=OHR.SummerDogs_FR-FR6348684869_1920x1080.jpg",
    "date": "2022-07-03",
    "title": "Héros de La Fontaine",
    "copyright": "Renard roux (© Yossi Eshbol/Minden Pictures)",
    "copyrightlink": "https://www.bing.com/search?q=renard+roux&FORM=hpcapt&filters=HpDate%3a%2220220702_2200%22"
  },
  "20220704": {
    "url": "https://www.bing.com/th?id=OHR.SharavatiBridge_FR-FR8627925896_1920x1080.jpg",
    "date": "2022-07-04",
    "title": "Prouesse d’ingénierie",
    "copyright": "Un train traversant le pont Sharavati dans le Karnataka, Inde (© Amith Nag Photography/Getty Images)",
    "copyrightlink": "https://www.bing.com/search?q=Karnataka&form=hpcapt&filters=HpDate%3a%2220220703_2200%22"
  },
  "20220705": {
    "url": "https://www.bing.com/th?id=OHR.BacResults_FR-FR9657922695_1920x1080.jpg",
    "date": "2022-07-05",
    "title": "Roulement de tambour",
    "copyright": "Cérémonie de remise des diplômes à l’américaine, Troyes (© Andia/Getty Images)",
    "copyrightlink": "https://www.bing.com/search?q=baccalaur%C3%A9at+en+France+&form=hpcapt&filters=HpDate%3a%2220220704_2200%22"
  },
  "20220706": {
    "url": "https://www.bing.com/th?id=OHR.KissingPuffins_FR-FR0969841182_1920x1080.jpg",
    "date": "2022-07-06",
    "title": "Baisers d’oiseaux",
    "copyright": "Deux macareux moines sur les îles Shetland, Écosse (© Vince Burton/Minden Pictures)",
    "copyrightlink": "https://www.bing.com/search?q=macareux+moine&form=hpcapt&filters=HpDate%3a%2220220705_2200%22"
  },
  "20220707": {
    "url": "https://www.bing.com/th?id=OHR.HecetaHead_FR-FR1420463940_1920x1080.jpg",
    "date": "2022-07-07",
    "title": "Un phare aux mille facettes",
    "copyright": "Phare Heceta Head, Florence, Oregon, USA (© Tom Schwabel/Tandem Stills + Motion)",
    "copyrightlink": "https://www.bing.com/search?q=C%C3%B4te+de+l%27Oregon+&form=hpcapt&filters=HpDate%3a%2220220706_2200%22"
  },
  "20220708": {
    "url": "https://www.bing.com/th?id=OHR.PreveliGorge_FR-FR1736023158_1920x1080.jpg",
    "date": "2022-07-08",
    "title": "La meilleure escale",
    "copyright": "Gorges de Préveli bordées par des forêts de palmiers, Crète, Grèce (© borchee/Getty Images)",
    "copyrightlink": "https://www.bing.com/search?q=cr%C3%A8te&form=hpcapt&filters=HpDate%3a%2220220707_2200%22"
  },
  "20220709": {
    "url": "https://www.bing.com/th?id=OHR.DolomitesMW_FR-FR3124362500_1920x1080.jpg",
    "date": "2022-07-09",
    "title": "Et là-haut, le ciel",
    "copyright": "Les Dolomites et la Voie Lactée, Italie (© Carlos Fernandez/Getty Images)",
    "copyrightlink": "https://www.bing.com/search?q=Dolomites&form=hpcapt&filters=HpDate%3a%2220220708_2200%22"
  },
  "20220710": {
    "url": "https://www.bing.com/th?id=OHR.OludenizTurkey_FR-FR3449178322_1920x1080.jpg",
    "date": "2022-07-10",
    "title": "Le bleu de Turquie",
    "copyright": "Vue aérienne de bateaux colorés sur la mer Méditerranée, Ölüdeniz, Turquie (© den-belitsky/Getty Images)",
    "copyrightlink": "https://www.bing.com/search?q=%C3%96l%C3%BCdeniz&form=hpcapt&filters=HpDate%3a%2220220709_2200%22"
  },
  "20220711": {
    "url": "https://www.bing.com/th?id=OHR.BarcelonaPop_FR-FR3835377255_1920x1080.jpg",
    "date": "2022-07-11",
    "title": "Une vraie fourmilière",
    "copyright": "Barcelone, Espagne (© SW Photography/Getty Images)",
    "copyrightlink": "https://www.bing.com/search?q=barcelona&form=hpcapt&filters=HpDate%3a%2220220710_2200%22"
  },
  "20220712": {
    "url": "https://www.bing.com/th?id=OHR.SpiralHill_FR-FR4074154737_1920x1080.jpg",
    "date": "2022-07-12",
    "title": "Vestige olympique",
    "copyright": "Point de vue Bay Marker, Parc Olympique de Sydney, Australie (© ai_yoshi/Getty Images)",
    "copyrightlink": "https://www.bing.com/search?q=Parc+olympique+de+Sydney&form=hpcapt&filters=HpDate%3a%2220220711_2200%22"
  },
  "20220713": {
    "url": "https://www.bing.com/th?id=OHR.BasaltGiants_FR-FR4350435529_1920x1080.jpg",
    "date": "2022-07-13",
    "title": "La Chaussée des Géants",
    "copyright": "Colonnes de basalte de la Chaussée des Géants, Irlande du Nord, Royaume-Uni (© Olimpio Fantuz/eStock Photo)",
    "copyrightlink": "https://www.bing.com/search?q=Chauss%C3%A9e+des+G%C3%A9ants%2c+irlande+du+nord&form=hpcapt&filters=HpDate%3a%2220220712_2200%22"
  },
  "20220714": {
    "url": "https://www.bing.com/th?id=OHR.ByeByeMonarchy_FR-FR9849572801_1920x1080.jpg",
    "date": "2022-07-14",
    "title": "La belle Marianne",
    "copyright": "Collection de timbres représentant Marianne, symbole de la République française (© Virginie Schleiermacher/Alamy Stock Photo)",
    "copyrightlink": "https://www.bing.com/search?q=f%C3%AAte+nationale+fran%C3%A7aise+&form=hpcapt&filters=HpDate%3a%2220220713_2200%22"
  },
  "20220715": {
    "url": "https://www.bing.com/th?id=OHR.Arrone_FR-FR1468008337_1920x1080.jpg",
    "date": "2022-07-15",
    "title": "Figé dans le temps",
    "copyright": "Le village d’Arrone en Ombrie, Italie (© Maurizio Rellini/eStock Photo)",
    "copyrightlink": "https://www.bing.com/search?q=arrone&form=hpcapt&filters=HpDate%3a%2220220714_2200%22"
  },
  "20220716": {
    "url": "https://www.bing.com/th?id=OHR.AmericanGoldfinch_FR-FR1636751984_1920x1080.jpg",
    "date": "2022-07-16",
    "title": "Ton sur ton",
    "copyright": "Chardonneret jaune sur un tournesol à McConnells, Caroline du Sud, États-Unis (© Teresa Kopec/Getty Images)",
    "copyrightlink": "https://www.bing.com/search?q=Chardonneret+jaune&form=hpcapt&filters=HpDate%3a%2220220715_2200%22"
  },
  "20220717": {
    "url": "https://www.bing.com/th?id=OHR.CoyoteButtes_FR-FR1848007907_1920x1080.jpg",
    "date": "2022-07-17",
    "title": "La Vague",
    "copyright": "Formation rocheuse 'The Wave’ dans le Coyote Buttes North, Paria Canyon-Vermilion Cliffs National Monument, Arizona, États-Unis (© Dennis Frates/Alamy)",
    "copyrightlink": "https://www.bing.com/search?q=coyote+buttes+north&form=hpcapt&filters=HpDate%3a%2220220716_2200%22"
  },
  "20220718": {
    "url": "https://www.bing.com/th?id=OHR.OmijimaIsland_FR-FR2031215669_1920x1080.jpg",
    "date": "2022-07-18",
    "title": "Le Japon fête l’océan",
    "copyright": "L’île Omijima dans le Parc quasi national de Kita-Nagato Kaigan, Japon (© Sean Pavone Photo/Adobe Stock)",
    "copyrightlink": "https://www.bing.com/search?q=Parc+quasi+national+de+Kita-Nagato+Kaigan&form=hpcapt&filters=HpDate%3a%2220220717_2200%22"
  },
  "20220719": {
    "url": "https://www.bing.com/th?id=OHR.StPaul_FR-FR2354587881_1920x1080.jpg",
    "date": "2022-07-19",
    "title": "Un art de Provence",
    "copyright": "Allée fleurie à Saint-Paul-de-Vence, Alpes Maritimes, Provence-Alpes-Côte-D’azur (© Susanne Kremer/Huber/eStock Photo)",
    "copyrightlink": "https://www.bing.com/search?q=Saint+paul+de+vence&form=hpcapt&filters=HpDate%3a%2220220718_2200%22"
  },
  "20220720": {
    "url": "https://www.bing.com/th?id=OHR.MoonPhases_FR-FR2824957504_1920x1080.jpg",
    "date": "2022-07-20",
    "title": "Lunaire",
    "copyright": "Image composite montrant les différentes phases de la lune (© Delpixart/Getty Images)",
    "copyrightlink": "https://www.bing.com/search?q=la+lune&form=hpcapt&filters=HpDate%3a%2220220719_2200%22"
  },
  "20220721": {
    "url": "https://www.bing.com/th?id=OHR.AbbeyGardens_FR-FR3048585399_1920x1080.jpg",
    "date": "2022-07-21",
    "title": "Symétriquement vôtre",
    "copyright": "Les jardins de l’abbey de Bury St Edmunds, Suffolk, Angleterre (© Charles Martinez/Amazing Aerial Agency)",
    "copyrightlink": "https://www.bing.com/search?q=bury+st+edmunds+angleterre&form=hpcapt&filters=HpDate%3a%2220220720_2200%22"
  },
  "20220722": {
    "url": "https://www.bing.com/th?id=OHR.SGIMontenegro_FR-FR3392947908_1920x1080.jpg",
    "date": "2022-07-22",
    "title": "La force de la foi",
    "copyright": "Notre Dame du Rocher sur l’île Saint Georges, dans les Bouches de Kotor, Perast, Montenegro (© Dmitrii Sakharov/Shutterstock)",
    "copyrightlink": "https://www.bing.com/search?q=bouches+de+kotor&form=hpcapt&filters=HpDate%3a%2220220721_2200%22"
  },
  "20220723": {
    "url": "https://www.bing.com/th?id=OHR.SailAway_FR-FR3636501249_1920x1080.jpg",
    "date": "2022-07-23",
    "title": "La Bretagne, ça nous gagne",
    "copyright": "Voiliers au crépuscule devant un phare au large de Roscoff, Finistère, Bretagne (© Cristina Granena/iStock/Getty Images Plus)",
    "copyrightlink": "https://www.bing.com/search?q=roscoff&form=hpcapt&filters=HpDate%3a%2220220722_2200%22"
  },
  "20220724": {
    "url": "https://www.bing.com/th?id=OHR.AmeliaEarhart_FR-FR4184656369_1920x1080.jpg",
    "date": "2022-07-24",
    "title": "Une vie héroïque",
    "copyright": "Amelia Earhart en train d’enseigner à Newark, New Jersey, USA (© Bettmann/Getty Images)",
    "copyrightlink": "https://www.bing.com/search?q=amelia+earhart&form=hpcapt&filters=HpDate%3a%2220220723_2200%22"
  },
  "20220725": {
    "url": "https://www.bing.com/th?id=OHR.MGRBrighton_FR-FR4940041141_1920x1080.jpg",
    "date": "2022-07-25",
    "title": "Tournez manège !",
    "copyright": "Le carrousel Golden Gallopers sur la plage de Brighton, East Sussex, Angleterre  (© Graham Prentice/Alamy)",
    "copyrightlink": "https://www.bing.com/search?q=carrousel+attraction+&form=hpcapt&filters=HpDate%3a%2220220724_2200%22"
  },
  "20220726": {
    "url": "https://www.bing.com/th?id=OHR.MangroveDay_FR-FR5496299343_1920x1080.jpg",
    "date": "2022-07-26",
    "title": "Gardienne de nos littoraux",
    "copyright": "Forêt de mangrove dans le parc national du delta du Saloum, Sénégal (© mariusz_prusaczyk/Getty Images)",
    "copyrightlink": "https://www.bing.com/search?q=Parc+national+du+delta+du+Saloum&form=hpcapt&filters=HpDate%3a%2220220725_2200%22"
  },
  "20220727": {
    "url": "https://www.bing.com/th?id=OHR.NabateanTomb_FR-FR5825302383_1920x1080.jpg",
    "date": "2022-07-27",
    "title": "Le château isolé",
    "copyright": "Tombes nabatéennes à Madain Saleh (Hégra), Arabie Saoudite (© Tuul & Bruno Morandi/Getty Images)",
    "copyrightlink": "https://www.bing.com/search?q=Madain+Saleh&form=hpcapt&filters=HpDate%3a%2220220726_2200%22"
  },
  "20220728": {
    "url": "https://www.bing.com/th?id=OHR.LongsPeak_FR-FR6011302355_1920x1080.jpg",
    "date": "2022-07-28",
    "title": "Le plus haut sommet",
    "copyright": "Pic Longs dans le parc national de Rocky Mountain, Colorado, États-Unis (© Andrew R. Slaton/Tandem Stills + Motion)",
    "copyrightlink": "https://www.bing.com/search?q=parc+national+de+rocky+mountain+colorado&form=hpcapt&filters=HpDate%3a%2220220727_2200%22"
  },
  "20220729": {
    "url": "https://www.bing.com/th?id=OHR.FourTigresses_FR-FR1714859277_1920x1080.jpg",
    "date": "2022-07-29",
    "title": "Beautés en danger",
    "copyright": "Tigresses dans le parc national de Tadoba, Inde (© Ashish Parmar/Alamy)",
    "copyrightlink": "https://www.bing.com/search?q=Tigre&form=hpcapt&filters=HpDate%3a%2220220728_2200%22"
  },
  "20220730": {
    "url": "https://www.bing.com/th?id=OHR.FiordlandRainforest_FR-FR8457095937_1920x1080.jpg",
    "date": "2022-07-30",
    "title": "La huitième merveille du monde",
    "copyright": "Randonnée dans une forêt tropicale près du Milford Sound/Piopiotahi en Nouvelle-Zélande (© Jim Patterson/Tandem Stills + Motion)",
    "copyrightlink": "https://www.bing.com/search?q=Milford+Sound&form=hpcapt&filters=HpDate%3a%2220220729_2200%22"
  },
  "20220731": {
    "url": "https://www.bing.com/th?id=OHR.NoctilucentClouds_FR-FR8706012918_1920x1080.jpg",
    "date": "2022-07-31",
    "title": "Drôles de nuages",
    "copyright": "Nuages noctulescents en Lituanie (© ljphoto7/Getty Images)",
    "copyrightlink": "https://www.bing.com/search?q=Nuage+noctulescent&form=hpcapt&filters=HpDate%3a%2220220730_2200%22"
  }
}