{
  "20200301": {
    "url": "https://www.bing.com/th?id=OHR.WallaceFF_EN-US1967284462_1920x1080.jpg",
    "date": "2020-03-01",
    "title": "It's leap day!",
    "copyright": "A Wallace's flying frog glides to the forest floor (© Stephen Dalton/Minden Pictures)",
    "copyrightlink": ""
  },
  "20200302": {
    "url": "https://www.bing.com/th?id=OHR.HikersVoters_EN-US2077085885_1920x1080.jpg",
    "date": "2020-03-02",
    "title": "Casting a vote for women's history",
    "copyright": "Women's suffragists who walked from New York City to Washington, DC, to join the National American Woman Suffrage Association parade on March 3, 1913 (© Everett Collection/age fotostock)",
    "copyrightlink": ""
  },
  "20200303": {
    "url": "https://www.bing.com/th?id=OHR.SeussianLandscape_EN-US2146844247_1920x1080.jpg",
    "date": "2020-03-03",
    "title": "And to think that I saw it in Cappadocia",
    "copyright": "Fairy chimneys and cave dwellings in Uçhisar, Cappadocia, Turkey (© Ivan Kmit/Alamy)",
    "copyrightlink": ""
  },
  "20200304": {
    "url": "https://www.bing.com/th?id=OHR.SpectralTarsiers_EN-US2290390785_1920x1080.jpg",
    "date": "2020-03-04",
    "title": "All eyes on sustainability",
    "copyright": "Spectral tarsiers in a ficus tree in Tangkoko Batuangus Nature Reserve, Indonesia (© Ondrej Prosicky/Shutterstock)",
    "copyrightlink": ""
  },
  "20200305": {
    "url": "https://www.bing.com/th?id=OHR.ElPit_EN-US2350184760_1920x1080.jpg",
    "date": "2020-03-05",
    "title": "A different kind of dive",
    "copyright": "Divers at El Pit cenote, located in Sistema Dos Ojos, Quintana Roo, Mexico (© Christia Vizl/Tandem Stills + Motion)",
    "copyrightlink": ""
  },
  "20200306": {
    "url": "https://www.bing.com/th?id=OHR.CarnegieaGigantea_EN-US2414292735_1920x1080.jpg",
    "date": "2020-03-06",
    "title": "The desert blooms",
    "copyright": "Saguaro cactus flowers, Coronado National Forest, Arizona (© Jack Dykinga/Minden Pictures)",
    "copyrightlink": ""
  },
  "20200307": {
    "url": "https://www.bing.com/th?id=OHR.BluebirdsYNP_EN-US2456710517_1920x1080.jpg",
    "date": "2020-03-07",
    "title": "Hello, harbinger of spring",
    "copyright": "Male mountain bluebird in Yellowstone National Park, Wyoming (© Jason Savage/Tandem Stills + Motion)",
    "copyrightlink": ""
  },
  "20200308": {
    "url": "https://www.bing.com/th?id=OHR.BronteBaths_EN-US9467599141_1920x1080.jpg",
    "date": "2020-03-08",
    "title": "Summer winds down in the Southern Hemisphere",
    "copyright": "Bird's-eye view of Bronte Baths ocean pool outside Sydney, Australia (© Shay Cooper/Media Drum World/Cavan Images)",
    "copyrightlink": ""
  },
  "20200309": {
    "url": "https://www.bing.com/th?id=OHR.JoanNYC_EN-US2569219288_1920x1080.jpg",
    "date": "2020-03-09",
    "title": "Joan charges Riverside Park",
    "copyright": "The Joan of Arc Monument at Riverside Park in Manhattan (© Chase Guttman/Alamy)",
    "copyrightlink": ""
  },
  "20200310": {
    "url": "https://www.bing.com/th?id=OHR.SnoozyTheBear_EN-US2658340968_1920x1080.jpg",
    "date": "2020-03-10",
    "title": "This grizzly has Napping Day down",
    "copyright": "Grizzly bear cub relaxing, Cook Inlet, Chinitna Bay, Lake Clark National Park and Preserve, Alaska (© Erlend Krumsvik/Getty Images)",
    "copyrightlink": ""
  },
  "20200311": {
    "url": "https://www.bing.com/th?id=OHR.DoljatraPowder_EN-US8224224106_1920x1080.jpg",
    "date": "2020-03-11",
    "title": "A festival  of colors",
    "copyright": "Brightly colored powder for sale during Holi (© Max Bauerfeind/Shutterstock)",
    "copyrightlink": ""
  },
  "20200312": {
    "url": "https://www.bing.com/th?id=OHR.CubsEmerge_EN-US2822084703_1920x1080.jpg",
    "date": "2020-03-12",
    "title": "Anybody out there?",
    "copyright": "Polar bear cubs looking out of their den in Wapusk National Park, Manitoba, Canada (© Robert Harding/Alamy)",
    "copyrightlink": ""
  },
  "20200313": {
    "url": "https://www.bing.com/th?id=OHR.FrenchColorado_ZH-CN9446885520_1920x1080.jpg",
    "date": "2020-03-13",
    "title": "",
    "copyright": "泰河畔伊尔的Les Orgues，法国北加泰罗尼亚 (© SFL Choice/Alamy)",
    "copyrightlink": ""
  },
  "20200314": {
    "url": "https://www.bing.com/th?id=OHR.JerteCherries_EN-US9711617537_1920x1080.jpg",
    "date": "2020-03-14",
    "title": "Jerte Valley in bloom",
    "copyright": "Blooming cherry trees in the Jerte Valley, province of Cáceres, Spain (© Westend61/Getty Images)",
    "copyrightlink": ""
  },
  "20200315": {
    "url": "https://www.bing.com/th?id=OHR.Cirkelbroen_EN-US9451869319_1920x1080.jpg",
    "date": "2020-03-15",
    "title": "A circular celebration",
    "copyright": "The Circle Bridge in Copenhagen, Denmark (© Lingxiao Xie/Getty Images)",
    "copyrightlink": ""
  },
  "20200316": {
    "url": "https://www.bing.com/th?id=OHR.MetamorphicRocks_EN-US9509651378_1920x1080.jpg",
    "date": "2020-03-16",
    "title": "Celebrating 200 years of statehood",
    "copyright": "Pemaquid Point Light in Maine's Damariscotta region (© Tom Whitney/Adobe Stock)",
    "copyrightlink": ""
  },
  "20200317": {
    "url": "https://www.bing.com/th?id=OHR.SirThomasMore_EN-US9546326212_1920x1080.jpg",
    "date": "2020-03-17",
    "title": "'I'll call for pen and ink…'",
    "copyright": "Shakespeare's handwriting from the play 'Sir Thomas More,' British Library, London (© British Library/Alamy)",
    "copyrightlink": ""
  },
  "20200318": {
    "url": "https://www.bing.com/th?id=OHR.Knowth_EN-US9596233080_1920x1080.jpg",
    "date": "2020-03-18",
    "title": "It's a good day to be green",
    "copyright": "Knowth burial mound in the Boyne Valley, Ireland, for St Patrick's Day (© whatapicture/plainpicture)",
    "copyrightlink": ""
  },
  "20200319": {
    "url": "https://www.bing.com/th?id=OHR.RobertCurbeam_EN-US9633185364_1920x1080.jpg",
    "date": "2020-03-19",
    "title": "A stroll above the stratosphere",
    "copyright": "NASA astronaut works on the International Space Station during a spacewalk in 2006 (© NASA)",
    "copyrightlink": ""
  },
  "20200320": {
    "url": "https://www.bing.com/th?id=OHR.EquinoxAngkor_EN-US9664645165_1920x1080.jpg",
    "date": "2020-03-20",
    "title": "Sunburst at Angkor",
    "copyright": "Sunrise at Angkor Wat in Cambodia (© Sergio Diaz/Getty Images)",
    "copyrightlink": ""
  },
  "20200321": {
    "url": "https://www.bing.com/th?id=OHR.SaltonSea_EN-US9699729653_1920x1080.jpg",
    "date": "2020-03-21",
    "title": "Heron lies the Salton Sea",
    "copyright": "A heron perches on a piling at the Salton Sea in California (© Garret Suhrie/Cavan Images)",
    "copyrightlink": ""
  },
  "20200322": {
    "url": "https://www.bing.com/th?id=OHR.PabloNeruda_EN-US9874244430_1920x1080.jpg",
    "date": "2020-03-22",
    "title": "It's World Poetry Day",
    "copyright": "Portrait of poet Pablo Neruda projected on a building, Santiago, Chile (© Mario Tellez/Anadolu Agency/Getty Images)",
    "copyrightlink": ""
  },
  "20200323": {
    "url": "https://www.bing.com/th?id=OHR.StepWell_EN-US9916978488_1920x1080.jpg",
    "date": "2020-03-23",
    "title": "Celebrating World Water Day",
    "copyright": "Women climbing a stepwell near Amber Fort in Jaipur, Rajasthan, India (© Shanna Baker/Offset)",
    "copyrightlink": ""
  },
  "20200324": {
    "url": "https://www.bing.com/th?id=OHR.LenticularVideo_EN-US3256283499_1920x1080.jpg",
    "date": "2020-03-24",
    "title": "A peak in the clouds",
    "copyright": "Lenticular clouds over Mount Rainier, Washington (© Delrious/Shutterstock)",
    "copyrightlink": ""
  },
  "20200325": {
    "url": "https://www.bing.com/th?id=OHR.SpainBeeEaters_EN-US0011186052_1920x1080.jpg",
    "date": "2020-03-25",
    "title": "Springtime in the Mediterranean",
    "copyright": "European bee-eaters in the Extremadura region of Spain (© Martin Demmel/Offset)",
    "copyrightlink": ""
  },
  "20200326": {
    "url": "https://www.bing.com/th?id=OHR.RadcliffeCamera_EN-US0047487559_1920x1080.jpg",
    "date": "2020-03-26",
    "title": "It's Tolkien Reading Day",
    "copyright": "The Radcliffe Camera, Oxford, England, for Tolkien Reading Day (© Joe Daniel Price/Getty Images)",
    "copyrightlink": ""
  },
  "20200327": {
    "url": "https://www.bing.com/th?id=OHR.NoCaliCoast_EN-US0095184591_1920x1080.jpg",
    "date": "2020-03-27",
    "title": "Gray days ahead in Monterey",
    "copyright": "Aerial view of the Big Sur coastline near Monterey, California (© Blue Planet Archive/Alamy)",
    "copyrightlink": ""
  },
  "20200328": {
    "url": "https://www.bing.com/th?id=OHR.CharlestonAzaleas_EN-US1112132446_1920x1080.jpg",
    "date": "2020-03-28",
    "title": "Pretty in pink, and purple, and red…",
    "copyright": "Azaleas in bloom at Magnolia Plantation and Gardens, Charleston, South Carolina (© Joanne Wells/Danita Delimont)",
    "copyrightlink": ""
  },
  "20200329": {
    "url": "https://www.bing.com/th?id=OHR.FormentorHolidays_EN-US1927408350_1920x1080.jpg",
    "date": "2020-03-29",
    "title": "The meeting point of the winds",
    "copyright": "Formentor Lighthouse at the tip of Cap de Formentor, Mallorca, Spain (© Lasse Eklöf/DEEPOL by plainpicture)",
    "copyrightlink": ""
  },
  "20200330": {
    "url": "https://www.bing.com/th?id=OHR.BorrowingDays_EN-US1332727011_1920x1080.jpg",
    "date": "2020-03-30",
    "title": "The borrowed days are here",
    "copyright": "A European crested tit weathers a storm in Scotland (© Ben Hall/Minden Pictures)",
    "copyrightlink": ""
  },
  "20200331": {
    "url": "https://www.bing.com/th?id=OHR.GalesnjakIsland_EN-US8495200916_1920x1080.jpg",
    "date": "2020-03-31",
    "title": "Spread some love with Bing",
    "copyright": "Aerial view of Galešnjak Island on the Adriatic coast of Croatia (© biggunsband/Shutterstock)",
    "copyrightlink": ""
  }
}